GenerarDB.py
generardb-1.3.2.dist-info/METADATA
generardb-1.3.2.dist-info/WHEEL
generardb-1.3.2.dist-info/top_level.txt
generardb-1.3.2.dist-info/RECORD
