Metadata-Version: 2.4
Name: GenerarDB
Version: 1.3.2
Summary: Librería para manejar bases de datos SQLite con facilidad.
Home-page: https://github.com/GhostmanBY/GenerarDB
Author: Nahuel Romero
Author-email: nahuelromero2709@gmail.com
License: MIT
Classifier: Programming Language :: Python :: 3
Classifier: License :: OSI Approved :: MIT License
Classifier: Operating System :: OS Independent
Requires-Python: >=3.6
Dynamic: author
Dynamic: author-email
Dynamic: classifier
Dynamic: home-page
Dynamic: license
Dynamic: requires-python
Dynamic: summary
